{"type":"FeatureCollection","features":[{"type":"Feature","properties":{"severity":"EF0"},"geometry":{"type":"Point","coordinates":[-86.0532084128609,33.86280050227986]}},{"type":"Feature","properties":{"severity":"EF0"},"geometry":{"type":"Point","coordinates":[-86.03968922576476,33.86734443319795]}},{"type":"Feature","properties":{"severity":"EF0"},"geometry":{"type":"Point","coordinates":[-86.15946022088333,33.860315886515416]}},{"type":"Feature","properties":{"severity":"EF0"},"geometry":{"type":"Point","coordinates":[-85.84770535390099,33.74970956241338]}},{"type":"Feature","properties":{"severity":"EF0"},"geometry":{"type":"Point","coordinates":[-87.58101044462455,30.448709031370356]}},{"type":"Feature","properties":{"severity":"EF0"},"geometry":{"type":"Point","coordinates":[-87.68180813895799,30.36549178714469]}},{"type":"Feature","properties":{"severity":"EF0"},"geometry":{"type":"Point","coordinates":[-87.67646296655188,30.378549770651272]}},{"type":"Feature","properties":{"severity":"EF1"},"geometry":{"type":"Point","coordinates":[-86.34707583027236,33.857814648700895]}},{"type":"Feature","properties":{"severity":"EF1"},"geometry":{"type":"Point","coordinates":[-86.34175647349255,33.85940126685016]}},{"type":"Feature","properties":{"severity":"EF1"},"geometry":{"type":"Point","coordinates":[-86.84747935485848,34.293287493443884]}},{"type":"Feature","properties":{"severity":"EF1"},"geometry":{"type":"Point","coordinates":[-86.9451454379228,34.33789303991574]}},{"type":"Feature","properties":{"severity":"EF1"},"geometry":{"type":"Point","coordinates":[-86.82535613859861,34.960751768608205]}},{"type":"Feature","properties":{"severity":"EF1"},"geometry":{"type":"Point","coordinates":[-86.19034972893432,34.460546970130174]}},{"type":"Feature","properties":{"severity":"EF1"},"geometry":{"type":"Point","coordinates":[-86.10959419904194,34.630953126225904]}},{"type":"Feature","properties":{"severity":"EF1"},"geometry":{"type":"Point","coordinates":[-85.89463577326849,33.83635827807288]}},{"type":"Feature","properties":{"severity":"EF2"},"geometry":{"type":"Point","coordinates":[-87.02451555536491,34.95706315197533]}},{"type":"Feature","properties":{"severity":"EF2"},"geometry":{"type":"Point","coordinates":[-86.80965059887204,34.960146962013006]}},{"type":"Feature","properties":{"severity":"EF2"},"geometry":{"type":"Point","coordinates":[-86.82535613859861,34.960751768608205]}},{"type":"Feature","properties":{"severity":"EF2"},"geometry":{"type":"Point","coordinates":[-86.09134447834265,33.86286933871225]}},{"type":"Feature","properties":{"severity":"EF2"},"geometry":{"type":"Point","coordinates":[-86.06777836527397,33.87222127867906]}},{"type":"Feature","properties":{"severity":"EF2"},"geometry":{"type":"Point","coordinates":[-86.09041358698647,33.86341000252619]}},{"type":"Feature","properties":{"severity":"EF2"},"geometry":{"type":"Point","coordinates":[-86.0990781938066,33.866792036484064]}},{"type":"Feature","properties":{"severity":"EF2"},"geometry":{"type":"Point","coordinates":[-86.02968082949027,33.87390413499913]}},{"type":"Feature","properties":{"severity":"EF2"},"geometry":{"type":"Point","coordinates":[-86.0487991309255,33.86538135726321]}},{"type":"Feature","properties":{"severity":"EF2"},"geometry":{"type":"Point","coordinates":[-86.0240242671227,33.87169218583422]}},{"type":"Feature","properties":{"severity":"EF2"},"geometry":{"type":"Point","coordinates":[-86.0532084128609,33.86280050227986]}},{"type":"Feature","properties":{"severity":"EF2"},"geometry":{"type":"Point","coordinates":[-86.03968922576476,33.86734443319795]}},{"type":"Feature","properties":{"severity":"EF2"},"geometry":{"type":"Point","coordinates":[-86.02638728978043,33.87835539695482]}},{"type":"Feature","properties":{"severity":"EF2"},"geometry":{"type":"Point","coordinates":[-86.04785161062472,33.865764366290186]}},{"type":"Feature","properties":{"severity":"EF2"},"geometry":{"type":"Point","coordinates":[-85.9881690256115,33.88276177289932]}},{"type":"Feature","properties":{"severity":"EF2"},"geometry":{"type":"Point","coordinates":[-86.03667878464663,33.87545597852905]}},{"type":"Feature","properties":{"severity":"EF2"},"geometry":{"type":"Point","coordinates":[-86.04397398305206,33.87912454679933]}},{"type":"Feature","properties":{"severity":"EF2"},"geometry":{"type":"Point","coordinates":[-86.15946022088333,33.860315886515416]}},{"type":"Feature","properties":{"severity":"EF2"},"geometry":{"type":"Point","coordinates":[-86.07566984520717,33.86369069609467]}},{"type":"Feature","properties":{"severity":"EF2"},"geometry":{"type":"Point","coordinates":[-86.06831993711104,33.86196740219652]}},{"type":"Feature","properties":{"severity":"EF2"},"geometry":{"type":"Point","coordinates":[-86.14653196491862,33.86593359553933]}},{"type":"Feature","properties":{"severity":"EF2"},"geometry":{"type":"Point","coordinates":[-86.18371532698684,33.857756693821436]}},{"type":"Feature","properties":{"severity":"EF2"},"geometry":{"type":"Point","coordinates":[-86.18361919903967,33.85685298768248]}},{"type":"Feature","properties":{"severity":"EF3"},"geometry":{"type":"Point","coordinates":[-85.36723614878,33.76767501118197]}},{"type":"Feature","properties":{"severity":"EF3"},"geometry":{"type":"Point","coordinates":[-85.44127655697054,33.783195630503265]}},{"type":"Feature","properties":{"severity":"EF3"},"geometry":{"type":"Point","coordinates":[-85.9400449776301,33.840840440768524]}},{"type":"Feature","properties":{"severity":"EF3"},"geometry":{"type":"Point","coordinates":[-85.69373037661057,33.820007030920074]}},{"type":"Feature","properties":{"severity":"EF3"},"geometry":{"type":"Point","coordinates":[-85.55977993814936,33.79475330913094]}},{"type":"Feature","properties":{"severity":"EF3"},"geometry":{"type":"Point","coordinates":[-85.8540603667627,33.838359303696954]}},{"type":"Feature","properties":{"severity":"EF3"},"geometry":{"type":"Point","coordinates":[-85.89463577326849,33.83635827807288]}},{"type":"Feature","properties":{"severity":"EF3"},"geometry":{"type":"Point","coordinates":[-85.86464415939315,33.832198544480036]}},{"type":"Feature","properties":{"severity":"EF3"},"geometry":{"type":"Point","coordinates":[-85.89681085759764,33.84499578550175]}},{"type":"Feature","properties":{"severity":"EF3"},"geometry":{"type":"Point","coordinates":[-85.87870676671342,33.83555872564957]}},{"type":"Feature","properties":{"severity":"EF3"},"geometry":{"type":"Point","coordinates":[-85.86496267641604,33.836330876765466]}}]}