{"type":"FeatureCollection","features":[{"type":"Feature","properties":{"severity":"EF0"},"geometry":{"type":"Point","coordinates":[-89.79553177773442,39.08252987295844]}},{"type":"Feature","properties":{"severity":"EF1"},"geometry":{"type":"Point","coordinates":[-88.68452435112273,42.43182714474288]}},{"type":"Feature","properties":{"severity":"EF1"},"geometry":{"type":"Point","coordinates":[-88.73999534697316,42.39211845292448]}},{"type":"Feature","properties":{"severity":"EF1"},"geometry":{"type":"Point","coordinates":[-88.69886023143854,41.36680692182327]}},{"type":"Feature","properties":{"severity":"EF1"},"geometry":{"type":"Point","coordinates":[-90.15474854681172,39.078081797309615]}},{"type":"Feature","properties":{"severity":"EF1"},"geometry":{"type":"Point","coordinates":[-89.61969961636851,39.13807653295686]}},{"type":"Feature","properties":{"severity":"EF1"},"geometry":{"type":"Point","coordinates":[-89.71234119604458,39.10792134995387]}},{"type":"Feature","properties":{"severity":"EF3"},"geometry":{"type":"Point","coordinates":[-88.90565883461191,41.32767077263601]}}]}