{"type":"FeatureCollection","features":[{"type":"Feature","properties":{"severity":"EF2"},"geometry":{"type":"Point","coordinates":[-89.55123321363675,37.37737130007925]}},{"type":"Feature","properties":{"severity":"EF0"},"geometry":{"type":"Point","coordinates":[-89.89477259093476,36.56522701658522]}},{"type":"Feature","properties":{"severity":"EF0"},"geometry":{"type":"Point","coordinates":[-89.88479958623454,36.5663152426365]}},{"type":"Feature","properties":{"severity":"EF0"},"geometry":{"type":"Point","coordinates":[-94.28678609349708,38.96649690144069]}},{"type":"Feature","properties":{"severity":"EF0"},"geometry":{"type":"Point","coordinates":[-94.29287816731156,38.97116761785438]}},{"type":"Feature","properties":{"severity":"EF0"},"geometry":{"type":"Point","coordinates":[-94.30899697449301,38.9882090697793]}},{"type":"Feature","properties":{"severity":"EF0"},"geometry":{"type":"Point","coordinates":[-94.30575527299888,38.983586995413695]}},{"type":"Feature","properties":{"severity":"EF0"},"geometry":{"type":"Point","coordinates":[-94.28823661602888,38.9683492055006]}},{"type":"Feature","properties":{"severity":"EF0"},"geometry":{"type":"Point","coordinates":[-94.30433525958507,38.98473419339793]}},{"type":"Feature","properties":{"severity":"EF0"},"geometry":{"type":"Point","coordinates":[-94.26848300547131,38.947504668889174]}},{"type":"Feature","properties":{"severity":"EF0"},"geometry":{"type":"Point","coordinates":[-94.27272103480027,38.95111078616358]}},{"type":"Feature","properties":{"severity":"EF0"},"geometry":{"type":"Point","coordinates":[-94.27416800302099,38.954834670934915]}},{"type":"Feature","properties":{"severity":"EF0"},"geometry":{"type":"Point","coordinates":[-94.26578523285066,38.94656671434199]}},{"type":"Feature","properties":{"severity":"EF0"},"geometry":{"type":"Point","coordinates":[-93.11402272492262,37.283954731045476]}},{"type":"Feature","properties":{"severity":"EF1"},"geometry":{"type":"Point","coordinates":[-93.13110104412539,37.26577653867065]}},{"type":"Feature","properties":{"severity":"EF2"},"geometry":{"type":"Point","coordinates":[-89.46614046085344,37.41172620356635]}},{"type":"Feature","properties":{"severity":"EF1"},"geometry":{"type":"Point","coordinates":[-93.60270738431429,37.624421180484795]}},{"type":"Feature","properties":{"severity":"EF2"},"geometry":{"type":"Point","coordinates":[-89.59281668811731,37.35778931701574]}},{"type":"Feature","properties":{"severity":"EF2"},"geometry":{"type":"Point","coordinates":[-89.51486073901202,37.39761886773055]}},{"type":"Feature","properties":{"severity":"EF2"},"geometry":{"type":"Point","coordinates":[-89.5808512307299,37.36531506446921]}},{"type":"Feature","properties":{"severity":"EF2"},"geometry":{"type":"Point","coordinates":[-89.58286161220242,37.360994923924736]}},{"type":"Feature","properties":{"severity":"EF2"},"geometry":{"type":"Point","coordinates":[-89.57760186085233,37.36694115950118]}},{"type":"Feature","properties":{"severity":"EF2"},"geometry":{"type":"Point","coordinates":[-89.47369565492548,37.41018682096009]}},{"type":"Feature","properties":{"severity":"EF2"},"geometry":{"type":"Point","coordinates":[-89.51312461804518,37.39659252750095]}},{"type":"Feature","properties":{"severity":"EF2"},"geometry":{"type":"Point","coordinates":[-89.60271556613282,37.3532256184474]}},{"type":"Feature","properties":{"severity":"EF2"},"geometry":{"type":"Point","coordinates":[-89.51458747253407,37.39760056976942]}}]}