{"type":"FeatureCollection","features":[{"type":"Feature","properties":{"severity":"EF2"},"geometry":{"type":"Point","coordinates":[-90.7398253014003,33.94057129200713]}},{"type":"Feature","properties":{"severity":"EF0"},"geometry":{"type":"Point","coordinates":[-88.59545032461409,34.13422439248882]}},{"type":"Feature","properties":{"severity":"EF0"},"geometry":{"type":"Point","coordinates":[-88.59905643951667,34.12419190699239]}},{"type":"Feature","properties":{"severity":"EF0"},"geometry":{"type":"Point","coordinates":[-89.84074298235498,32.25708464692227]}},{"type":"Feature","properties":{"severity":"EF0"},"geometry":{"type":"Point","coordinates":[-89.83447144853484,32.274305493913445]}},{"type":"Feature","properties":{"severity":"EF0"},"geometry":{"type":"Point","coordinates":[-89.81448988410996,32.331968161767904]}},{"type":"Feature","properties":{"severity":"EF0"},"geometry":{"type":"Point","coordinates":[-90.89286336303421,32.26927286905218]}},{"type":"Feature","properties":{"severity":"EF1"},"geometry":{"type":"Point","coordinates":[-90.85712274308592,32.26323486203696]}},{"type":"Feature","properties":{"severity":"EF0"},"geometry":{"type":"Point","coordinates":[-90.17933063564206,32.3847400591695]}},{"type":"Feature","properties":{"severity":"EF0"},"geometry":{"type":"Point","coordinates":[-90.18048620341362,32.38097103061209]}},{"type":"Feature","properties":{"severity":"EF0"},"geometry":{"type":"Point","coordinates":[-90.17872266359115,32.381840174630135]}},{"type":"Feature","properties":{"severity":"EF0"},"geometry":{"type":"Point","coordinates":[-90.17736332950759,32.38335277369932]}},{"type":"Feature","properties":{"severity":"EF0"},"geometry":{"type":"Point","coordinates":[-90.17937113538746,32.378327345274435]}},{"type":"Feature","properties":{"severity":"EF1"},"geometry":{"type":"Point","coordinates":[-90.17804776018198,32.38552205057488]}},{"type":"Feature","properties":{"severity":"EF0"},"geometry":{"type":"Point","coordinates":[-90.17905789310883,32.37840755033446]}},{"type":"Feature","properties":{"severity":"EF0"},"geometry":{"type":"Point","coordinates":[-90.15946176210875,32.38176419256668]}},{"type":"Feature","properties":{"severity":"EF0"},"geometry":{"type":"Point","coordinates":[-90.17815325248263,32.38340994656007]}},{"type":"Feature","properties":{"severity":"EF1"},"geometry":{"type":"Point","coordinates":[-90.1576427280483,32.382266833898264]}},{"type":"Feature","properties":{"severity":"EF0"},"geometry":{"type":"Point","coordinates":[-90.14423844364325,32.37470033301342]}},{"type":"Feature","properties":{"severity":"EF1"},"geometry":{"type":"Point","coordinates":[-90.13207844911013,32.37089215384243]}},{"type":"Feature","properties":{"severity":"EF1"},"geometry":{"type":"Point","coordinates":[-90.14521536513429,32.3760232307732]}},{"type":"Feature","properties":{"severity":"EF1"},"geometry":{"type":"Point","coordinates":[-90.13005217721444,32.370318322526884]}},{"type":"Feature","properties":{"severity":"EF0"},"geometry":{"type":"Point","coordinates":[-89.44111098681641,31.453836489693305]}},{"type":"Feature","properties":{"severity":"EF1"},"geometry":{"type":"Point","coordinates":[-89.67340043548869,30.520967011206412]}},{"type":"Feature","properties":{"severity":"EF1"},"geometry":{"type":"Point","coordinates":[-89.66498757450718,30.525139917459565]}},{"type":"Feature","properties":{"severity":"EF0"},"geometry":{"type":"Point","coordinates":[-89.06695882932351,30.37876092431753]}},{"type":"Feature","properties":{"severity":"EF0"},"geometry":{"type":"Point","coordinates":[-89.00454499923588,30.39774951792346]}},{"type":"Feature","properties":{"severity":"EF0"},"geometry":{"type":"Point","coordinates":[-89.05835279988337,30.387013164284298]}},{"type":"Feature","properties":{"severity":"EF0"},"geometry":{"type":"Point","coordinates":[-89.0047567462144,30.395743758012916]}},{"type":"Feature","properties":{"severity":"EF0"},"geometry":{"type":"Point","coordinates":[-89.00170887344599,30.40277901889216]}},{"type":"Feature","properties":{"severity":"EF0"},"geometry":{"type":"Point","coordinates":[-89.00553369432976,30.392403901481213]}},{"type":"Feature","properties":{"severity":"EF0"},"geometry":{"type":"Point","coordinates":[-89.00241964982786,30.399932712142803]}},{"type":"Feature","properties":{"severity":"EF0"},"geometry":{"type":"Point","coordinates":[-89.00667821536261,30.392425112917827]}},{"type":"Feature","properties":{"severity":"EF0"},"geometry":{"type":"Point","coordinates":[-89.0039215966148,30.39883742439808]}},{"type":"Feature","properties":{"severity":"EF0"},"geometry":{"type":"Point","coordinates":[-89.00367647661533,30.395651340245085]}},{"type":"Feature","properties":{"severity":"EF0"},"geometry":{"type":"Point","coordinates":[-88.98702311475635,30.41210730557552]}},{"type":"Feature","properties":{"severity":"EF0"},"geometry":{"type":"Point","coordinates":[-88.98996445979844,30.404836990076145]}},{"type":"Feature","properties":{"severity":"EF0"},"geometry":{"type":"Point","coordinates":[-88.99248863215357,30.398483654978275]}},{"type":"Feature","properties":{"severity":"EF0"},"geometry":{"type":"Point","coordinates":[-88.98722885124954,30.41342425216769]}},{"type":"Feature","properties":{"severity":"EF0"},"geometry":{"type":"Point","coordinates":[-88.97677526029797,30.40634566254117]}},{"type":"Feature","properties":{"severity":"EF0"},"geometry":{"type":"Point","coordinates":[-89.00078883219221,30.402310399622863]}},{"type":"Feature","properties":{"severity":"EF0"},"geometry":{"type":"Point","coordinates":[-88.98603164963087,30.413991504749983]}},{"type":"Feature","properties":{"severity":"EF0"},"geometry":{"type":"Point","coordinates":[-88.99178835135314,30.399599144284952]}},{"type":"Feature","properties":{"severity":"EF0"},"geometry":{"type":"Point","coordinates":[-88.99255392280205,30.39743654460987]}},{"type":"Feature","properties":{"severity":"EF0"},"geometry":{"type":"Point","coordinates":[-88.9917095087978,30.403252998714855]}},{"type":"Feature","properties":{"severity":"EF0"},"geometry":{"type":"Point","coordinates":[-88.99422447814057,30.39779301576218]}},{"type":"Feature","properties":{"severity":"EF0"},"geometry":{"type":"Point","coordinates":[-88.99165084933551,30.40493803201357]}},{"type":"Feature","properties":{"severity":"EF0"},"geometry":{"type":"Point","coordinates":[-88.97367489088677,30.43478927527286]}},{"type":"Feature","properties":{"severity":"EF0"},"geometry":{"type":"Point","coordinates":[-89.17573652162132,30.346741105311974]}},{"type":"Feature","properties":{"severity":"EF0"},"geometry":{"type":"Point","coordinates":[-89.1767051244592,30.35682458517085]}},{"type":"Feature","properties":{"severity":"EF0"},"geometry":{"type":"Point","coordinates":[-89.17604196019242,30.36466820140532]}},{"type":"Feature","properties":{"severity":"EF0"},"geometry":{"type":"Point","coordinates":[-89.1775790297838,30.348492167083702]}},{"type":"Feature","properties":{"severity":"EF0"},"geometry":{"type":"Point","coordinates":[-89.17569867460621,30.363311277918505]}},{"type":"Feature","properties":{"severity":"EF0"},"geometry":{"type":"Point","coordinates":[-88.49837673334699,30.46379237522172]}},{"type":"Feature","properties":{"severity":"EF0"},"geometry":{"type":"Point","coordinates":[-88.51470932169212,30.412279770116065]}},{"type":"Feature","properties":{"severity":"EF0"},"geometry":{"type":"Point","coordinates":[-88.52108164867677,30.401091987068106]}},{"type":"Feature","properties":{"severity":"EF0"},"geometry":{"type":"Point","coordinates":[-88.50392246724799,30.450973247495163]}},{"type":"Feature","properties":{"severity":"EF0"},"geometry":{"type":"Point","coordinates":[-88.52338735211451,30.398258794609973]}},{"type":"Feature","properties":{"severity":"EF0"},"geometry":{"type":"Point","coordinates":[-88.50905125048693,30.431342674022087]}},{"type":"Feature","properties":{"severity":"EF0"},"geometry":{"type":"Point","coordinates":[-88.5287067141827,30.391481049982286]}},{"type":"Feature","properties":{"severity":"EF0"},"geometry":{"type":"Point","coordinates":[-88.51779481680455,30.405506594256327]}},{"type":"Feature","properties":{"severity":"EF0"},"geometry":{"type":"Point","coordinates":[-88.51748908820356,30.407093144086755]}},{"type":"Feature","properties":{"severity":"EF0"},"geometry":{"type":"Point","coordinates":[-89.28569986754947,30.311823370420676]}},{"type":"Feature","properties":{"severity":"EF0"},"geometry":{"type":"Point","coordinates":[-89.28297007995604,30.30939052344304]}},{"type":"Feature","properties":{"severity":"EF0"},"geometry":{"type":"Point","coordinates":[-89.28632107479571,30.312189186999863]}},{"type":"Feature","properties":{"severity":"EF0"},"geometry":{"type":"Point","coordinates":[-89.5769831103962,30.257022934888546]}},{"type":"Feature","properties":{"severity":"EF0"},"geometry":{"type":"Point","coordinates":[-89.37327381475615,30.27911183496845]}},{"type":"Feature","properties":{"severity":"EF0"},"geometry":{"type":"Point","coordinates":[-89.3870299238198,30.30805624742646]}},{"type":"Feature","properties":{"severity":"EF0"},"geometry":{"type":"Point","coordinates":[-89.3746023660657,30.278640269099267]}},{"type":"Feature","properties":{"severity":"EF0"},"geometry":{"type":"Point","coordinates":[-89.3858661972792,30.308960550552285]}},{"type":"Feature","properties":{"severity":"EF0"},"geometry":{"type":"Point","coordinates":[-89.3922728239335,30.291562819617145]}},{"type":"Feature","properties":{"severity":"EF0"},"geometry":{"type":"Point","coordinates":[-89.39175836271663,30.2890623000824]}},{"type":"Feature","properties":{"severity":"EF0"},"geometry":{"type":"Point","coordinates":[-89.36978232480391,30.298348280841065]}},{"type":"Feature","properties":{"severity":"EF0"},"geometry":{"type":"Point","coordinates":[-89.38153780988755,30.284790591552152]}},{"type":"Feature","properties":{"severity":"EF0"},"geometry":{"type":"Point","coordinates":[-89.37630000390831,30.28010321092413]}},{"type":"Feature","properties":{"severity":"EF0"},"geometry":{"type":"Point","coordinates":[-89.38169498989775,30.305947834786323]}},{"type":"Feature","properties":{"severity":"EF0"},"geometry":{"type":"Point","coordinates":[-89.38855212430943,30.287855193724354]}},{"type":"Feature","properties":{"severity":"EF0"},"geometry":{"type":"Point","coordinates":[-90.54676308149062,31.618331138525594]}},{"type":"Feature","properties":{"severity":"EF0"},"geometry":{"type":"Point","coordinates":[-90.52026825466305,31.611333759732148]}},{"type":"Feature","properties":{"severity":"EF0"},"geometry":{"type":"Point","coordinates":[-90.57373323856476,31.601059530774258]}},{"type":"Feature","properties":{"severity":"EF0"},"geometry":{"type":"Point","coordinates":[-90.51719938485891,31.608730058779482]}},{"type":"Feature","properties":{"severity":"EF1"},"geometry":{"type":"Point","coordinates":[-88.79738085196955,34.21240956408363]}},{"type":"Feature","properties":{"severity":"EF1"},"geometry":{"type":"Point","coordinates":[-88.81555824970106,34.20004270238553]}},{"type":"Feature","properties":{"severity":"EF1"},"geometry":{"type":"Point","coordinates":[-88.8391957156964,34.18214540312594]}},{"type":"Feature","properties":{"severity":"EF1"},"geometry":{"type":"Point","coordinates":[-88.72715712715822,34.25023122062366]}},{"type":"Feature","properties":{"severity":"EF1"},"geometry":{"type":"Point","coordinates":[-88.81023249760581,34.20246495233373]}},{"type":"Feature","properties":{"severity":"EF1"},"geometry":{"type":"Point","coordinates":[-88.82977732854629,34.19027552681652]}},{"type":"Feature","properties":{"severity":"EF1"},"geometry":{"type":"Point","coordinates":[-88.73028895529782,34.24933809787067]}},{"type":"Feature","properties":{"severity":"EF1"},"geometry":{"type":"Point","coordinates":[-88.82199478013771,34.19353342619642]}},{"type":"Feature","properties":{"severity":"EF1"},"geometry":{"type":"Point","coordinates":[-88.63119045601384,34.30565185500517]}},{"type":"Feature","properties":{"severity":"EF1"},"geometry":{"type":"Point","coordinates":[-88.7145268327204,34.261823002473115]}},{"type":"Feature","properties":{"severity":"EF1"},"geometry":{"type":"Point","coordinates":[-88.71718974615125,34.25780831891253]}},{"type":"Feature","properties":{"severity":"EF1"},"geometry":{"type":"Point","coordinates":[-88.59098033027311,34.334791567067796]}},{"type":"Feature","properties":{"severity":"EF1"},"geometry":{"type":"Point","coordinates":[-88.67646675102868,34.28145410211717]}},{"type":"Feature","properties":{"severity":"EF1"},"geometry":{"type":"Point","coordinates":[-88.70414241786266,34.26594535556509]}},{"type":"Feature","properties":{"severity":"EF1"},"geometry":{"type":"Point","coordinates":[-88.60766624900096,34.32237423977142]}},{"type":"Feature","properties":{"severity":"EF1"},"geometry":{"type":"Point","coordinates":[-88.66653231154865,34.28790505773809]}},{"type":"Feature","properties":{"severity":"EF1"},"geometry":{"type":"Point","coordinates":[-88.58634200169254,34.33759476073915]}},{"type":"Feature","properties":{"severity":"EF1"},"geometry":{"type":"Point","coordinates":[-89.91080348851942,32.08102837501418]}},{"type":"Feature","properties":{"severity":"EF1"},"geometry":{"type":"Point","coordinates":[-90.33510314015749,32.42709914140043]}},{"type":"Feature","properties":{"severity":"EF1"},"geometry":{"type":"Point","coordinates":[-90.33393519757482,32.427587165979645]}},{"type":"Feature","properties":{"severity":"EF1"},"geometry":{"type":"Point","coordinates":[-90.37265333573191,32.431392935633255]}},{"type":"Feature","properties":{"severity":"EF1"},"geometry":{"type":"Point","coordinates":[-90.33522599001401,32.42530697745322]}},{"type":"Feature","properties":{"severity":"EF1"},"geometry":{"type":"Point","coordinates":[-90.33068292793129,32.425708781373295]}},{"type":"Feature","properties":{"severity":"EF1"},"geometry":{"type":"Point","coordinates":[-90.37837566049387,32.43953886084949]}},{"type":"Feature","properties":{"severity":"EF1"},"geometry":{"type":"Point","coordinates":[-90.4061397201552,32.44289153424863]}},{"type":"Feature","properties":{"severity":"EF1"},"geometry":{"type":"Point","coordinates":[-90.89922406274833,31.875735970787144]}},{"type":"Feature","properties":{"severity":"EF1"},"geometry":{"type":"Point","coordinates":[-90.23722272637447,32.4015579046739]}},{"type":"Feature","properties":{"severity":"EF1"},"geometry":{"type":"Point","coordinates":[-89.67413257764507,33.23510524183611]}},{"type":"Feature","properties":{"severity":"EF1"},"geometry":{"type":"Point","coordinates":[-90.84200733844861,32.25931350908786]}},{"type":"Feature","properties":{"severity":"EF1"},"geometry":{"type":"Point","coordinates":[-90.83836734167247,32.2587651016849]}},{"type":"Feature","properties":{"severity":"EF1"},"geometry":{"type":"Point","coordinates":[-90.8807374701964,32.265316379159536]}},{"type":"Feature","properties":{"severity":"EF1"},"geometry":{"type":"Point","coordinates":[-90.89994206283968,32.26882103286896]}},{"type":"Feature","properties":{"severity":"EF1"},"geometry":{"type":"Point","coordinates":[-90.83749932443898,32.26038827731106]}},{"type":"Feature","properties":{"severity":"EF1"},"geometry":{"type":"Point","coordinates":[-89.3632783293062,32.59958357851909]}},{"type":"Feature","properties":{"severity":"EF1"},"geometry":{"type":"Point","coordinates":[-90.37340940665263,32.821066791057305]}},{"type":"Feature","properties":{"severity":"EF1"},"geometry":{"type":"Point","coordinates":[-90.18693302013156,32.38556560865358]}},{"type":"Feature","properties":{"severity":"EF1"},"geometry":{"type":"Point","coordinates":[-90.15717994911343,32.382769730130995]}},{"type":"Feature","properties":{"severity":"EF1"},"geometry":{"type":"Point","coordinates":[-90.18713377606625,32.380337158987075]}},{"type":"Feature","properties":{"severity":"EF1"},"geometry":{"type":"Point","coordinates":[-90.16434802575888,32.3832197577266]}},{"type":"Feature","properties":{"severity":"EF1"},"geometry":{"type":"Point","coordinates":[-90.14806743240474,32.37681525457978]}},{"type":"Feature","properties":{"severity":"EF1"},"geometry":{"type":"Point","coordinates":[-90.17477837940483,32.38508219638146]}},{"type":"Feature","properties":{"severity":"EF1"},"geometry":{"type":"Point","coordinates":[-90.17418525478892,32.38719684827177]}},{"type":"Feature","properties":{"severity":"EF1"},"geometry":{"type":"Point","coordinates":[-90.15680354503013,32.38338394009369]}},{"type":"Feature","properties":{"severity":"EF1"},"geometry":{"type":"Point","coordinates":[-90.1563001510417,32.380646695132036]}},{"type":"Feature","properties":{"severity":"EF1"},"geometry":{"type":"Point","coordinates":[-90.15942352892729,32.384669990107696]}},{"type":"Feature","properties":{"severity":"EF1"},"geometry":{"type":"Point","coordinates":[-90.17207091961028,32.385920629589904]}},{"type":"Feature","properties":{"severity":"EF1"},"geometry":{"type":"Point","coordinates":[-90.15453279758225,32.38246194904244]}},{"type":"Feature","properties":{"severity":"EF1"},"geometry":{"type":"Point","coordinates":[-90.18784599314979,32.3872387692303]}},{"type":"Feature","properties":{"severity":"EF1"},"geometry":{"type":"Point","coordinates":[-90.15601114668267,32.38352310766556]}},{"type":"Feature","properties":{"severity":"EF1"},"geometry":{"type":"Point","coordinates":[-90.18105391721421,32.38577582387352]}},{"type":"Feature","properties":{"severity":"EF1"},"geometry":{"type":"Point","coordinates":[-90.15659581904545,32.38143731966972]}},{"type":"Feature","properties":{"severity":"EF1"},"geometry":{"type":"Point","coordinates":[-90.17308972131666,32.38698705692606]}},{"type":"Feature","properties":{"severity":"EF1"},"geometry":{"type":"Point","coordinates":[-90.184497399515,32.38508934068464]}},{"type":"Feature","properties":{"severity":"EF1"},"geometry":{"type":"Point","coordinates":[-90.179461416798,32.38580756835269]}},{"type":"Feature","properties":{"severity":"EF1"},"geometry":{"type":"Point","coordinates":[-90.1564986589106,32.38141034909627]}},{"type":"Feature","properties":{"severity":"EF1"},"geometry":{"type":"Point","coordinates":[-90.1556983949405,32.38091338610515]}},{"type":"Feature","properties":{"severity":"EF1"},"geometry":{"type":"Point","coordinates":[-90.18698299815446,32.38524002756133]}},{"type":"Feature","properties":{"severity":"EF1"},"geometry":{"type":"Point","coordinates":[-90.19240856544909,32.387852065174556]}},{"type":"Feature","properties":{"severity":"EF1"},"geometry":{"type":"Point","coordinates":[-90.1685164096014,32.385393006608375]}},{"type":"Feature","properties":{"severity":"EF1"},"geometry":{"type":"Point","coordinates":[-90.16025399298944,32.38474675394091]}},{"type":"Feature","properties":{"severity":"EF1"},"geometry":{"type":"Point","coordinates":[-90.18851233756078,32.38518659924257]}},{"type":"Feature","properties":{"severity":"EF1"},"geometry":{"type":"Point","coordinates":[-90.16462179781817,32.384732267298624]}},{"type":"Feature","properties":{"severity":"EF1"},"geometry":{"type":"Point","coordinates":[-90.15496643825232,32.3824670374353]}},{"type":"Feature","properties":{"severity":"EF1"},"geometry":{"type":"Point","coordinates":[-90.18634814890375,32.37952441726516]}},{"type":"Feature","properties":{"severity":"EF1"},"geometry":{"type":"Point","coordinates":[-90.19049057402451,32.38807328310383]}},{"type":"Feature","properties":{"severity":"EF1"},"geometry":{"type":"Point","coordinates":[-90.13371785180254,32.371055714595]}},{"type":"Feature","properties":{"severity":"EF1"},"geometry":{"type":"Point","coordinates":[-90.10944040730244,32.364791963732195]}},{"type":"Feature","properties":{"severity":"EF1"},"geometry":{"type":"Point","coordinates":[-90.12669382789161,32.36914980834148]}},{"type":"Feature","properties":{"severity":"EF1"},"geometry":{"type":"Point","coordinates":[-90.14156949334962,32.3763138972773]}},{"type":"Feature","properties":{"severity":"EF1"},"geometry":{"type":"Point","coordinates":[-90.13443851715616,32.375326022632834]}},{"type":"Feature","properties":{"severity":"EF1"},"geometry":{"type":"Point","coordinates":[-90.12452057909451,32.36989041497975]}},{"type":"Feature","properties":{"severity":"EF1"},"geometry":{"type":"Point","coordinates":[-90.11344579528077,32.365075689444424]}},{"type":"Feature","properties":{"severity":"EF1"},"geometry":{"type":"Point","coordinates":[-90.10309103971733,32.3629384698358]}},{"type":"Feature","properties":{"severity":"EF1"},"geometry":{"type":"Point","coordinates":[-90.14385309780045,32.37809662194747]}},{"type":"Feature","properties":{"severity":"EF1"},"geometry":{"type":"Point","coordinates":[-90.3011059933567,32.174625300841974]}},{"type":"Feature","properties":{"severity":"EF1"},"geometry":{"type":"Point","coordinates":[-90.30301095159393,32.16955836378893]}},{"type":"Feature","properties":{"severity":"EF1"},"geometry":{"type":"Point","coordinates":[-90.29512307120049,32.19282490368132]}},{"type":"Feature","properties":{"severity":"EF1"},"geometry":{"type":"Point","coordinates":[-90.30315738940206,32.172137172039314]}},{"type":"Feature","properties":{"severity":"EF1"},"geometry":{"type":"Point","coordinates":[-90.29999219958236,32.19897722960224]}},{"type":"Feature","properties":{"severity":"EF1"},"geometry":{"type":"Point","coordinates":[-90.29421527949013,32.19737188991372]}},{"type":"Feature","properties":{"severity":"EF1"},"geometry":{"type":"Point","coordinates":[-90.29659147229115,32.189435163369716]}},{"type":"Feature","properties":{"severity":"EF1"},"geometry":{"type":"Point","coordinates":[-89.10537607948027,31.98160059806649]}},{"type":"Feature","properties":{"severity":"EF1"},"geometry":{"type":"Point","coordinates":[-89.670094216368,30.522774590081152]}},{"type":"Feature","properties":{"severity":"EF1"},"geometry":{"type":"Point","coordinates":[-89.95587976093168,31.255814671255294]}},{"type":"Feature","properties":{"severity":"EF1"},"geometry":{"type":"Point","coordinates":[-89.37833060048217,30.375984725548378]}},{"type":"Feature","properties":{"severity":"EF1"},"geometry":{"type":"Point","coordinates":[-88.51491180686169,30.403113349830907]}},{"type":"Feature","properties":{"severity":"EF1"},"geometry":{"type":"Point","coordinates":[-89.28513974756856,30.322641528802894]}},{"type":"Feature","properties":{"severity":"EF1"},"geometry":{"type":"Point","coordinates":[-89.27008772542466,30.31835721302657]}},{"type":"Feature","properties":{"severity":"EF1"},"geometry":{"type":"Point","coordinates":[-89.28861354204804,30.323884316839045]}},{"type":"Feature","properties":{"severity":"EF1"},"geometry":{"type":"Point","coordinates":[-90.28340460869,31.62345745827571]}},{"type":"Feature","properties":{"severity":"EF1"},"geometry":{"type":"Point","coordinates":[-90.53079222263885,31.5326483557571]}},{"type":"Feature","properties":{"severity":"EF1"},"geometry":{"type":"Point","coordinates":[-90.52716314898372,31.525065697761416]}},{"type":"Feature","properties":{"severity":"EF1"},"geometry":{"type":"Point","coordinates":[-90.71945391686863,31.565216258559683]}}]}