{"type":"FeatureCollection","features":[{"type":"Feature","properties":{"severity":"EF0"},"geometry":{"type":"Point","coordinates":[-88.71504665148643,32.441060526421204]}},{"type":"Feature","properties":{"severity":"EF0"},"geometry":{"type":"Point","coordinates":[-88.6708499802387,32.45748132086212]}},{"type":"Feature","properties":{"severity":"EF0"},"geometry":{"type":"Point","coordinates":[-88.65822672745294,32.463690238425606]}},{"type":"Feature","properties":{"severity":"EF1"},"geometry":{"type":"Point","coordinates":[-90.07805058007287,33.96181191116151]}},{"type":"Feature","properties":{"severity":"EF1"},"geometry":{"type":"Point","coordinates":[-90.02059295838988,34.04092803727253]}},{"type":"Feature","properties":{"severity":"EF1"},"geometry":{"type":"Point","coordinates":[-90.31494501395004,33.0123900024331]}},{"type":"Feature","properties":{"severity":"EF1"},"geometry":{"type":"Point","coordinates":[-90.37197646304493,32.93282628714368]}},{"type":"Feature","properties":{"severity":"EF1"},"geometry":{"type":"Point","coordinates":[-90.37124213132422,32.93644594983425]}},{"type":"Feature","properties":{"severity":"EF1"},"geometry":{"type":"Point","coordinates":[-88.50310782393349,33.1596151546545]}},{"type":"Feature","properties":{"severity":"EF1"},"geometry":{"type":"Point","coordinates":[-88.72350117069963,30.398617586823608]}},{"type":"Feature","properties":{"severity":"EF2"},"geometry":{"type":"Point","coordinates":[-90.51494160790021,33.613491860149765]}},{"type":"Feature","properties":{"severity":"EF2"},"geometry":{"type":"Point","coordinates":[-89.88816957172688,33.12255472877496]}},{"type":"Feature","properties":{"severity":"EF2"},"geometry":{"type":"Point","coordinates":[-89.66080931787755,33.30096627085836]}},{"type":"Feature","properties":{"severity":"EF2"},"geometry":{"type":"Point","coordinates":[-89.71009149735715,33.28444297213561]}},{"type":"Feature","properties":{"severity":"EF3"},"geometry":{"type":"Point","coordinates":[-88.83272993237962,33.89325874674343]}},{"type":"Feature","properties":{"severity":"EF3"},"geometry":{"type":"Point","coordinates":[-88.79899520716708,33.907061828374104]}},{"type":"Feature","properties":{"severity":"EF3"},"geometry":{"type":"Point","coordinates":[-88.67240612156276,33.95685820178289]}},{"type":"Feature","properties":{"severity":"EF3"},"geometry":{"type":"Point","coordinates":[-88.74191102188004,33.9293244531102]}},{"type":"Feature","properties":{"severity":"EF3"},"geometry":{"type":"Point","coordinates":[-88.74941580789748,33.87877693402294]}},{"type":"Feature","properties":{"severity":"EF3"},"geometry":{"type":"Point","coordinates":[-88.50217989049084,31.175811268743555]}},{"type":"Feature","properties":{"severity":"EF3"},"geometry":{"type":"Point","coordinates":[-88.61734468061744,33.977874473527834]}},{"type":"Feature","properties":{"severity":"EF3"},"geometry":{"type":"Point","coordinates":[-88.70506856788985,33.9434526348218]}},{"type":"Feature","properties":{"severity":"EF3"},"geometry":{"type":"Point","coordinates":[-88.89683658008047,33.763158007039124]}},{"type":"Feature","properties":{"severity":"EF3"},"geometry":{"type":"Point","coordinates":[-88.86787907339445,33.79283042951576]}},{"type":"Feature","properties":{"severity":"EF3"},"geometry":{"type":"Point","coordinates":[-89.02185638982895,33.82056753679098]}},{"type":"Feature","properties":{"severity":"EF4"},"geometry":{"type":"Point","coordinates":[-88.82091966734849,32.160174864762375]}},{"type":"Feature","properties":{"severity":"EF4"},"geometry":{"type":"Point","coordinates":[-89.20818058920794,32.08908162681431]}},{"type":"Feature","properties":{"severity":"EF5"},"geometry":{"type":"Point","coordinates":[-88.86877871860467,32.92766306832959]}}]}